invariant_point_attention/__init__.py
invariant_point_attention/invariant_point_attention.py
invariant_point_attention/utils.py
invariant_point_attention-0.2.0.dist-info/LICENSE
invariant_point_attention-0.2.0.dist-info/METADATA
invariant_point_attention-0.2.0.dist-info/WHEEL
invariant_point_attention-0.2.0.dist-info/top_level.txt
invariant_point_attention-0.2.0.dist-info/RECORD
